htmloverpdf/__init__.py
htmloverpdf/__main__.py
htmloverpdf-0.0.3.dist-info/LICENSE
htmloverpdf-0.0.3.dist-info/METADATA
htmloverpdf-0.0.3.dist-info/WHEEL
htmloverpdf-0.0.3.dist-info/entry_points.txt
htmloverpdf-0.0.3.dist-info/top_level.txt
htmloverpdf-0.0.3.dist-info/RECORD
