Metadata-Version: 2.1
Name: htmloverpdf
Version: 0.0.3
Summary: Render a HTML overlay over existing PDF files.
Home-page: UNKNOWN
Author: Barnaby Shearer
Author-email: b@zi.is
License: UNKNOWN
Project-URL: Source, https://github.com/BarnabyShearer/htmloverpdf
Project-URL: Tracker, https://github.com/BarnabyShearer/htmloverpdf/issues
Project-URL: Documentation, https://htmloverpdf.readthedocs.io/en/latest/
Keywords: pdf
Platform: UNKNOWN
Classifier: Development Status :: 5 - Production/Stable
Classifier: License :: OSI Approved :: BSD License
Classifier: Programming Language :: Python :: 3
Requires-Python: >=3.7
License-File: LICENSE
Requires-Dist: weasyprint (<53)
Requires-Dist: pygobject
Requires-Dist: pycairo
Requires-Dist: cairocffi
Requires-Dist: lxml
Requires-Dist: lxml-stubs
